{  
    "雪糕":[
        "\n好饿，好想吃{丝袜颜色}{丝袜厚度}{丝袜种类}{丝袜长度}\n{%丝袜发癫文学}"
], 

"丝袜发癫文学":[
    "姐姐~这是什么呀~丝袜？没见过呢~可以脱下来给我嘛~那你穿什么？emmm姐姐穿秋裤吧~",
    "姐姐有一双脚而我刚刚好有一张嘴。",
    "我都不敢想象这有多好吃。",
    "姐姐，我吃不下了。",
    "开饭啦。",
    "就喜欢厚的味儿也更浓厚，就像咖啡一样。",
    "天冷啦！宝宝要保暖。",
    "宝宝，怎么这么好看。",
    "打给你了。",
    "这个我是真心喜欢。",
    "这穿完帮我闻闻香不香。",
    "有种别样的口感。",
    "加餐了！",
    "贫僧今天不打诳语，改打别的了。",
    "就这样不要脱。",
    "小孩子才会在意选项，要是我的话。早就抱起姐姐跑啦。",
    "软软的，香香的。"
],
    
"丝袜颜色":[
    "经典白色",
    "经典黑色"]
    ,
    
"丝袜种类":[
    "透明",
    "不透明",
    "网格",
    "蕾丝",
    "哑光"
],
"丝袜长度":[
    "中筒袜",
    "长筒袜",
    "过膝袜",
    "连裤袜",
    "踩脚袜"
] ,
    
"丝袜厚度":[
    "超薄",
    "一般薄",
    "中厚",
    "加厚",
    "超厚"
],
    
"性交姿势":[

    "狗狗姿势",
    "蝴蝶姿势",
    "摇篮姿势",
    "轿子姿势",
    "沙发姿势",
    "桥式",
    "桌子姿势",
    "椅子姿势",
    "倒立姿势",
    "悬挂姿势",
    "姿势",
    "捆绑姿势",
    "臀桥姿势",
    "捆绑式",
    "倒立式",
    "悬挂式",
    "穹窿姿势",
    "69式",
    "男上位",
    "女上位",
    "侧面位",
    "背插位",
    "坐位",
    "站立位",
    "后入式",
    "猫鼠同家",
    "羊上树",
    "吟猿抱树",
    "玄瞑鹏翥",
    "丹穴凤游",
    "昆鸡临场",
    "山羊对树",
    "玄蝉附",
    "白虎腾",
    "凤将雏",
    "月亮女神变形姿势",
    "传教士姿势",
    "眼镜蛇姿势",
    "眼镜蛇翻转姿势",
    "海底捞月姿势",
    "陀螺旋转姿势",
    "狗狗姿势",
    "月亮女神姿势",
    "摇篮变形姿势",
    "臀桥变形姿势",
    "蝴蝶翻转姿势",
    "穹窿变形姿势"
]
}